walletconstructor/__init__.py
walletconstructor/security.py
walletconstructor/wallet.py
walletAVA-0.1.2.dist-info/LICENSE
walletAVA-0.1.2.dist-info/METADATA
walletAVA-0.1.2.dist-info/WHEEL
walletAVA-0.1.2.dist-info/top_level.txt
walletAVA-0.1.2.dist-info/RECORD
