Metadata-Version: 2.1
Name: walletAVA
Version: 0.1.2
Summary: Module gestion wallet basee sur la blockchain ethereurm
Home-page: https://gitlab.com/kikakopjunior/walletweb3.git
Author: kikakop
Author-email: kikakopjunior@gmail.com
Classifier: Programming Language :: Python :: 3
Classifier: License :: OSI Approved :: MIT License
Classifier: Operating System :: OS Independent
Requires-Python: >=3.6
License-File: LICENSE
Requires-Dist: web3
Requires-Dist: cryptography
Requires-Dist: pathlib
Requires-Dist: requests
